topsis/__init__.py
topsis/topsis.py
Topsis_Yuvraj_10223293-1.0.0.dist-info/LICENSE
Topsis_Yuvraj_10223293-1.0.0.dist-info/METADATA
Topsis_Yuvraj_10223293-1.0.0.dist-info/WHEEL
Topsis_Yuvraj_10223293-1.0.0.dist-info/entry_points.txt
Topsis_Yuvraj_10223293-1.0.0.dist-info/top_level.txt
Topsis_Yuvraj_10223293-1.0.0.dist-info/RECORD
